hlsclt/__init__.py
hlsclt/_version.py
hlsclt/classes.py
hlsclt/helper_funcs.py
hlsclt/hlsclt.py
hlsclt/build_commands/__init__.py
hlsclt/build_commands/build_commands.py
hlsclt/clean_commands/__init__.py
hlsclt/clean_commands/clean_commands.py
hlsclt/examples/simple_adder/c
hlsclt/examples/simple_adder/hls_config.py
hlsclt/examples/simple_adder/run_hls.tcl
hlsclt/examples/simple_adder/vivado_hls.log
hlsclt/examples/simple_adder/proj_simple_adder/vivado_hls.app
hlsclt/examples/simple_adder/proj_simple_adder/solution1/hls_config.py
hlsclt/examples/simple_adder/proj_simple_adder/solution1/solution1.aps
hlsclt/examples/simple_adder/proj_simple_adder/solution1/solution1.directive
hlsclt/examples/simple_adder/proj_simple_adder/solution1/solution1.log
hlsclt/examples/simple_adder/proj_simple_adder/solution1/.autopilot/.automg_exit
hlsclt/examples/simple_adder/proj_simple_adder/solution1/.autopilot/.autopilot_exit
hlsclt/examples/simple_adder/proj_simple_adder/solution1/.autopilot/db/a.export.ll
hlsclt/examples/simple_adder/proj_simple_adder/solution1/.autopilot/db/a.g
hlsclt/examples/simple_adder/proj_simple_adder/solution1/.autopilot/db/a.g.0
hlsclt/examples/simple_adder/proj_simple_adder/solution1/.autopilot/db/a.g.0.bc
hlsclt/examples/simple_adder/proj_simple_adder/solution1/.autopilot/db/a.g.1.bc
hlsclt/examples/simple_adder/proj_simple_adder/solution1/.autopilot/db/a.g.1.ll
hlsclt/examples/simple_adder/proj_simple_adder/solution1/.autopilot/db/a.g.2.bc
hlsclt/examples/simple_adder/proj_simple_adder/solution1/.autopilot/db/a.g.2.prechk.bc
hlsclt/examples/simple_adder/proj_simple_adder/solution1/.autopilot/db/a.g.bc
hlsclt/examples/simple_adder/proj_simple_adder/solution1/.autopilot/db/a.g.ll
hlsclt/examples/simple_adder/proj_simple_adder/solution1/.autopilot/db/a.o
hlsclt/examples/simple_adder/proj_simple_adder/solution1/.autopilot/db/a.o.1.bc
hlsclt/examples/simple_adder/proj_simple_adder/solution1/.autopilot/db/a.o.1.ll
hlsclt-1.0.0a6.dist-info/LICENSE
hlsclt-1.0.0a6.dist-info/METADATA
hlsclt-1.0.0a6.dist-info/WHEEL
hlsclt-1.0.0a6.dist-info/entry_points.txt
hlsclt-1.0.0a6.dist-info/top_level.txt
hlsclt-1.0.0a6.dist-info/RECORD
