Metadata-Version: 2.1
Name: hlsclt
Version: 1.0.0a6
Summary: A Vivado HLS Command Line Helper Tool
Home-page: https://github.com/benjmarshall/hlsclt
Author: Ben Marshall
Author-email: sayhello@benmarshall.co.uk
License: MIT
Keywords: xilinx vivado development
Platform: UNKNOWN
Classifier: Development Status :: 3 - Alpha
Classifier: Intended Audience :: Developers
Classifier: Topic :: Software Development :: Build Tools
Classifier: License :: OSI Approved :: MIT License
Classifier: Programming Language :: Python :: 3.6
Classifier: Programming Language :: Python :: 2.7
Requires-Dist: Click
